{
  "updatedAt": "2026-07-14 21:00",
  "items": [
    {
      "group": "股市指數",
      "name": "台灣加權指數",
      "symbol": "^TWII",
      "price": 44737.95,
      "previousClose": 45380.52,
      "change": -642.5699999999997,
      "changePercent": -1.4159599757781527,
      "currency": "TWD"
    },
    {
      "group": "股市指數",
      "name": "中國A50",
      "symbol": "XIN9.FGI",
      "price": 15379.54,
      "previousClose": 15029.63,
      "change": 349.9100000000017,
      "changePercent": 2.3281344916674707,
      "currency": "CNY"
    },
    {
      "group": "股市指數",
      "name": "小道瓊",
      "symbol": "YM=F",
      "price": 52645.0,
      "previousClose": 52764.0,
      "change": -119.0,
      "changePercent": -0.22553256007884162,
      "currency": "USD"
    },
    {
      "group": "股市指數",
      "name": "小那斯達克",
      "symbol": "NQ=F",
      "price": 29797.25,
      "previousClose": 29475.75,
      "change": 321.5,
      "changePercent": 1.090727123143601,
      "currency": "USD"
    },
    {
      "group": "股市指數",
      "name": "德國DAX",
      "symbol": "^GDAXI",
      "price": 24979.55,
      "previousClose": 25114.25,
      "change": -134.70000000000073,
      "changePercent": -0.5363488855928437,
      "currency": "EUR"
    },
    {
      "group": "股市指數",
      "name": "恆生指數",
      "symbol": "^HSI",
      "price": 24340.73,
      "previousClose": 24213.72,
      "change": 127.0099999999984,
      "changePercent": 0.5245373284237135,
      "currency": "HKD"
    },
    {
      "group": "商品",
      "name": "黃金",
      "symbol": "GC=F",
      "price": 4089.8,
      "previousClose": 4005.7,
      "change": 84.10000000000036,
      "changePercent": 2.0995082008138497,
      "currency": "USD"
    },
    {
      "group": "商品",
      "name": "輕原油",
      "symbol": "CL=F",
      "price": 80.86,
      "previousClose": 78.14,
      "change": 2.719999999999999,
      "changePercent": 3.4809316611210632,
      "currency": "USD"
    },
    {
      "group": "匯率",
      "name": "美元",
      "symbol": "TWD=X",
      "price": 32.125,
      "previousClose": 32.171,
      "change": -0.045999999999999375,
      "changePercent": -0.14298591899536656,
      "currency": "TWD"
    },
    {
      "group": "匯率",
      "name": "歐元",
      "symbol": "EURTWD=X",
      "price": 36.802,
      "previousClose": 36.666,
      "change": 0.13600000000000279,
      "changePercent": 0.37091583483336826,
      "currency": "TWD"
    },
    {
      "group": "匯率",
      "name": "人民幣",
      "symbol": "CNYTWD=X",
      "price": 4.7491,
      "previousClose": 4.7483,
      "change": 0.0007999999999999119,
      "changePercent": 0.01684813512204182,
      "currency": "TWD"
    },
    {
      "group": "匯率",
      "name": "比特幣",
      "symbol": "BTC-USD",
      "price": 63816.86,
      "previousClose": 62259.16,
      "change": 1557.699999999997,
      "changePercent": 2.501961157201602,
      "currency": "USD"
    }
  ]
}
